dayuanlib/__init__.py
dayuanlib/_version.py
dayuanlib/dataprocessor.py
dayuanlib/tools.py
dayuanlib/xmlzip.py
dayuanlib-0.4.7.dist-info/METADATA
dayuanlib-0.4.7.dist-info/WHEEL
dayuanlib-0.4.7.dist-info/RECORD
