Metadata-Version: 2.4
Name: dayuanlib
Version: 0.4.7
Summary: Add your description here
Classifier: Framework :: Pydantic
Classifier: Framework :: Pydantic :: 1
Classifier: Framework :: Pydantic :: 2
Classifier: Intended Audience :: Developers
Classifier: Programming Language :: Python
Classifier: Programming Language :: Python :: 3
Classifier: Programming Language :: Python :: 3 :: Only
Classifier: Programming Language :: Python :: 3.8
Classifier: Programming Language :: Python :: 3.9
Classifier: Programming Language :: Python :: 3.10
Classifier: Programming Language :: Python :: 3.11
Classifier: Programming Language :: Python :: 3.12
Classifier: Programming Language :: Python :: 3.13
Classifier: Programming Language :: Python :: 3.14
Classifier: Typing :: Typed
Requires-Python: >=3.8.15
Requires-Dist: numpy>=1.24.4
Requires-Dist: scipy>=1.10.1
